COPYING.txt
MANIFEST.in
README.rst
setup.cfg
setup.py
rattail/__init__.py
rattail/_version.py
rattail/app.py
rattail/auth.py
rattail/backup.py
rattail/barcodes.py
rattail/board.py
rattail/cleanup.py
rattail/clientele.py
rattail/config.py
rattail/core.py
rattail/csvutil.py
rattail/custorders.py
rattail/daemon.py
rattail/emails.py
rattail/employment.py
rattail/enum.py
rattail/excel.py
rattail/exceptions.py
rattail/files.py
rattail/gpc.py
rattail/install.py
rattail/labels.py
rattail/logging.py
rattail/mail.py
rattail/mako.py
rattail/membership.py
rattail/monitoring.py
rattail/org.py
rattail/palm.py
rattail/people.py
rattail/pod.py
rattail/poddoc.py
rattail/pricing.py
rattail/products.py
rattail/progress.py
rattail/settings.py
rattail/tailbone.py
rattail/telemetry.py
rattail/threads.py
rattail/time.py
rattail/upgrades.py
rattail/util.py
rattail/webapi.py
rattail/wince.py
rattail/workorders.py
rattail.egg-info/PKG-INFO
rattail.egg-info/SOURCES.txt
rattail.egg-info/dependency_links.txt
rattail.egg-info/entry_points.txt
rattail.egg-info/requires.txt
rattail.egg-info/top_level.txt
rattail/autocomplete/__init__.py
rattail/autocomplete/base.py
rattail/autocomplete/brands.py
rattail/autocomplete/customers.py
rattail/autocomplete/departments.py
rattail/autocomplete/employees.py
rattail/autocomplete/members.py
rattail/autocomplete/people.py
rattail/autocomplete/products.py
rattail/autocomplete/subdepartments.py
rattail/autocomplete/vendors.py
rattail/batch/__init__.py
rattail/batch/custorder.py
rattail/batch/delproduct.py
rattail/batch/filemon.py
rattail/batch/handheld.py
rattail/batch/handlers.py
rattail/batch/importer.py
rattail/batch/inventory.py
rattail/batch/labels.py
rattail/batch/newproduct.py
rattail/batch/pos.py
rattail/batch/pricing.py
rattail/batch/product.py
rattail/batch/purchase.py
rattail/batch/util.py
rattail/batch/vendorcatalog.py
rattail/batch/vendorinvoice.py
rattail/bouncer/__init__.py
rattail/bouncer/config.py
rattail/bouncer/daemon.py
rattail/bouncer/filemon.py
rattail/bouncer/handler.py
rattail/commands/__init__.py
rattail/commands/backup.py
rattail/commands/base.py
rattail/commands/batch.py
rattail/commands/bouncer.py
