Metadata-Version: 2.1
Name: rattail
Version: 0.13.2
Summary: Retail Software Framework
Home-page: https://rattailproject.org/
Author: Lance Edgar
Author-email: lance@edbob.org
License: GNU GPL v3
Classifier: Development Status :: 4 - Beta
Classifier: Environment :: Console
Classifier: Environment :: Web Environment
Classifier: Environment :: Win32 (MS Windows)
Classifier: Environment :: X11 Applications
Classifier: Intended Audience :: Developers
Classifier: License :: OSI Approved :: GNU General Public License v3 or later (GPLv3+)
Classifier: Natural Language :: English
Classifier: Operating System :: OS Independent
Classifier: Programming Language :: Python
Classifier: Programming Language :: Python :: 3
Classifier: Programming Language :: Python :: 3.6
Classifier: Programming Language :: Python :: 3.7
Classifier: Programming Language :: Python :: 3.8
Classifier: Programming Language :: Python :: 3.9
Classifier: Programming Language :: Python :: 3.10
Classifier: Programming Language :: Python :: 3.11
Classifier: Topic :: Office/Business
Classifier: Topic :: Software Development :: Libraries :: Python Modules
Requires-Python: >=3.6
License-File: COPYING.txt
Requires-Dist: bcrypt
Requires-Dist: colander
Requires-Dist: humanize
Requires-Dist: importlib_metadata; python_version < "3.8"
Requires-Dist: lockfile
Requires-Dist: makefun
Requires-Dist: Mako
Requires-Dist: MarkupSafe
Requires-Dist: openpyxl
Requires-Dist: packaging
Requires-Dist: progress
Requires-Dist: pyinotify; sys_platform != "win32"
Requires-Dist: pytz
Requires-Dist: requests
Requires-Dist: six
Requires-Dist: texttable
Requires-Dist: typer
Requires-Dist: typing-extensions
Requires-Dist: WuttJamaican>=0.3.0
Requires-Dist: xlrd
Provides-Extra: bouncer
Requires-Dist: flufl.bounce<3.0; extra == "bouncer"
Provides-Extra: db
Requires-Dist: alembic; extra == "db"
Requires-Dist: beaker; extra == "db"
Requires-Dist: passlib; extra == "db"
Requires-Dist: SQLAlchemy<1.5,>=1.4; extra == "db"
Requires-Dist: SQLAlchemy-Continuum; extra == "db"
Provides-Extra: memcached
Requires-Dist: pylibmc; extra == "memcached"
Provides-Extra: supervisor
Requires-Dist: supervisor; extra == "supervisor"
Provides-Extra: docs
Requires-Dist: Sphinx; extra == "docs"
Requires-Dist: sphinx-paramlinks; extra == "docs"
Requires-Dist: sphinxcontrib-programoutput; extra == "docs"
Provides-Extra: tests
Requires-Dist: coverage; extra == "tests"
Requires-Dist: mock; extra == "tests"
Requires-Dist: pytest; extra == "tests"
Requires-Dist: pytest-cov; extra == "tests"
